Metadata-Version: 1.0
Name: django-enumerify
Version: 0.5.2
Summary: Simple Enums for Django when working with choices in model fields.
Home-page: http://bitbucket.org/willandskill/django-enumerify
Author: Faisal Mahmud
Author-email: faisal@willandskill.se
License: BSD licence, see LICENCE.txt
Platform: UNKNOWN
